{"FullPath":"C:\\Users\\nikol\\Source\\Repos\\dji-sdk\\Windows-SDK\\WSDK Libraries\\SDK dll x86\\DJIWindowsWrapper.winmd","InProcServers":{"DJIWindowsWrapper.dll":{"Path":"DJIWindowsWrapper.dll","TypeToThreadingModel":{"DJIWindowsWrapper.DecodingAssistInfo":"both","DJIWindowsWrapper.IMUMultipleOrientationCalibrationHint":"both","DJIWindowsWrapper.IntMinMax":"both","DJIWindowsWrapper.VideoResolutionFrameRate":"both","DJIWindowsWrapper.FCMotorStartFailureErrorMsg":"both","DJIWindowsWrapper.DoubleMsg":"both","DJIWindowsWrapper.SpeakerAudioFileUploadingInfo":"both","DJIWindowsWrapper.CameraColorRangeMsg":"both","DJIWindowsWrapper.GimbalAngleRotation":"both","DJIWindowsWrapper.GimbalAttitudeRange":"both","DJIWindowsWrapper.CameraDisplayModeMsg":"both","DJIWindowsWrapper.SpeakerAudioDataSendingResultMsg":"both","DJIWindowsWrapper.CameraThermalPaletteRangeMsg":"both","DJIWindowsWrapper.CameraExposureCompensationMsg":"both","DJIWindowsWrapper.CameraTemperatureUnitMsg":"both","DJIWindowsWrapper.PhotoBurstCountMsg":"both","DJIWindowsWrapper.WaypointMissionExecutionState":"both","DJIWindowsWrapper.BatteryHeatingStateMsg":"both","DJIWindowsWrapper.DJIWindowsWrappedInterfaces":"both","DJIWindowsWrapper.BoolMsg":"both","DJIWindowsWrapper.MediaTaskRequest":"both","DJIWindowsWrapper.WaypointMission":"both","DJIWindowsWrapper.AccessLockerFormattingProgressStateMsg":"both","DJIWindowsWrapper.CameraISOMsg":"both","DJIWindowsWrapper.MediaTaskResponse":"both","DJIWindowsWrapper.IMUState":"both","DJIWindowsWrapper.VissionDetectionState":"both","DJIWindowsWrapper.SDKActivationInfo":"both","DJIWindowsWrapper.IntPoint2D":"both","DJIWindowsWrapper.WiFiFrequencyBandMsg":"both","DJIWindowsWrapper.GoHomeAssessmentValue":"both","DJIWindowsWrapper.ObstacleDetectionSector":"both","DJIWindowsWrapper.CameraExposureModeMsg":"both","DJIWindowsWrapper.CameraAntiFlickerMsg":"both","DJIWindowsWrapper.CameraWhiteBalance":"both","DJIWindowsWrapper.IMUStates":"both","DJIWindowsWrapper.FlysafeLimitArea":"both","DJIWindowsWrapper.DoublePoint2D":"both","DJIWindowsWrapper.CameraPanoTypeMsg":"both","DJIWindowsWrapper.MediaFileDownloadRequest":"both","DJIWindowsWrapper.CameraFocusModeMsg":"both","DJIWindowsWrapper.PlayingAudioFileInfo":"both","DJIWindowsWrapper.FlysafeHeightLicenseInfo":"both","DJIWindowsWrapper.LandingProtectionStateMsg":"both","DJIWindowsWrapper.ThermalAreaTemperatureAggregationsMsg":"both","DJIWindowsWrapper.DoublePoint3D":"both","DJIWindowsWrapper.Attitude":"both","DJIWindowsWrapper.StringMsg":"both","DJIWindowsWrapper.EmptyMsg":"both","DJIWindowsWrapper.CameraThermalIsothermUnitMsg":"both","DJIWindowsWrapper.ProductTypeMsg":"both","DJIWindowsWrapper.DJIWindowsWrapperComponentHandler":"both","DJIWindowsWrapper.GeneratedMediaFileInfo":"both","DJIWindowsWrapper.CameraColorMsg":"both","DJIWindowsWrapper.FCGoHomeStateMsg":"both","DJIWindowsWrapper.AccessLockerUserAccountInfoMsg":"both","DJIWindowsWrapper.DoubleMinMax":"both","DJIWindowsWrapper.FlysafeLicenseGroupMsg":"both","DJIWindowsWrapper.SpeakerAudioSendingStateMsg":"both","DJIWindowsWrapper.VideoFileCompressionStandardMsg":"both","DJIWindowsWrapper.DateTime":"both","DJIWindowsWrapper.FCBatteryThresholdBehaviorMsg":"both","DJIWindowsWrapper.IntVector2D":"both","DJIWindowsWrapper.FCCompassCalibrationStateMsg":"both","DJIWindowsWrapper.MediaBatchFileRequestResult":"both","DJIWindowsWrapper.FlysafeAreaLicenseInfo":"both","DJIWindowsWrapper.CameraShootPhotoModeMsg":"both","DJIWindowsWrapper.DJIWindowsLocationHandle":"both","DJIWindowsWrapper.SimulatorInitializationSettings":"both","DJIWindowsWrapper.AccessLockerModifyAccountMsg":"both","DJIWindowsWrapper.VideoStorageFormatMsg":"both","DJIWindowsWrapper.CameraThermalROIMsg":"both","DJIWindowsWrapper.FileExifInfo":"both","DJIWindowsWrapper.SpeakerPlayModeTypeMsg":"both","DJIWindowsWrapper.FCGPSSignalLevelMsg":"both","DJIWindowsWrapper.FlysafeCircleLicenseInfo":"both","DJIWindowsWrapper.CameraSDCardStateMsg":"both","DJIWindowsWrapper.FCGPSModeFailureReasonMsg":"both","DJIWindowsWrapper.CameraOpticalZoomSpec":"both","DJIWindowsWrapper.CameraStorageLocationMsg":"both","DJIWindowsWrapper.LEDsSettings":"both","DJIWindowsWrapper.CameraMeteringModeMsg":"both","DJIWindowsWrapper.CameraAutoTurnOffLEDModeMsg":"both","DJIWindowsWrapper.AccessLockerStateMsg":"both","DJIWindowsWrapper.SpeakerAudioFilesIndexes":"both","DJIWindowsWrapper.WaypointMissionStateTransition":"both","DJIWindowsWrapper.DJIWindowsDatalinkHandler":"both","DJIWindowsWrapper.FlysafeLicenseGroup":"both","DJIWindowsWrapper.CameraShutterSpeedMsg":"both","DJIWindowsWrapper.CameraThermalFFCModeMsg":"both","DJIWindowsWrapper.Waypoint":"both","DJIWindowsWrapper.GimbalResetCommandMsg":"both","DJIWindowsWrapper.GimbalCalibrationState":"both","DJIWindowsWrapper.AirSenseAirplaneState":"both","DJIWindowsWrapper.CameraTypeMsg":"both","DJIWindowsWrapper.FlysafePolygonLicenseInfo":"both","DJIWindowsWrapper.CameraWatermarkSettings":"both","DJIWindowsWrapper.MediaFileList":"both","DJIWindowsWrapper.RCFlightModeSwitchMsg":"both","DJIWindowsWrapper.WaypointAction":"both","DJIWindowsWrapper.FCWindWarningMsg":"both","DJIWindowsWrapper.CameraWorkModeMsg":"both","DJIWindowsWrapper.DJIWindowsUSBHandler":"both","DJIWindowsWrapper.FCFlightModeMsg":"both","DJIWindowsWrapper.PhotoRatioMsg":"both","DJIWindowsWrapper.LocationCoordinate2D":"both","DJIWindowsWrapper.Velocity3D":"both","DJIWindowsWrapper.CameraFileIndexModeMsg":"both","DJIWindowsWrapper.PhotoStorageFormatMsg":"both","DJIWindowsWrapper.MediaStarTagRequest":"both","DJIWindowsWrapper.GimbalSpeedRotation":"both","DJIWindowsWrapper.SpeakerAudioDeleteFilesInfo":"both","DJIWindowsWrapper.IntMsg":"both","DJIWindowsWrapper.CameraOrientationMsg":"both","DJIWindowsWrapper.MediaFile":"both","DJIWindowsWrapper.FCAutoRTHReasonMsg":"both","DJIWindowsWrapper.AirSenseSystemInformation":"both","DJIWindowsWrapper.FlysafeLimitAreaMsg":"both","DJIWindowsWrapper.WaypointMissionUploadState":"both","DJIWindowsWrapper.CameraContinuousOpticalZoomParam":"both","DJIWindowsWrapper.MediaDeletionRequest":"both","DJIWindowsWrapper.FCFailsafeActionMsg":"both","DJIWindowsWrapper.MediaFileListLocationMsg":"both","DJIWindowsWrapper.DJIWindowsNetworkHandle":"both","DJIWindowsWrapper.WaypointMissionDownloadState":"both","DJIWindowsWrapper.CameraFocusStateMsg":"both","DJIWindowsWrapper.SpeakerAudioDataPack":"both","DJIWindowsWrapper.SpeakerFileRenameInfo":"both","DJIWindowsWrapper.SpeakerAudioFileInfo":"both","DJIWindowsWrapper.CameraThermalMeasurementModeMsg":"both","DJIWindowsWrapper.CameraActualFocusArea":"both","DJIWindowsWrapper.VisionSystemWarningMsg":"both","DJIWindowsWrapper.FCRemoteControllerSwitchModeMsg":"both","DJIWindowsWrapper.CameraThermalGainModeMsg":"both","DJIWindowsWrapper.FlysafeCountryLicenseInfo":"both","DJIWindowsWrapper.CameraThermalPaletteMsg":"both","DJIWindowsWrapper.CameraHistogram":"both","DJIWindowsWrapper.PhotoIntervalShootSettings":"both","DJIWindowsWrapper.MediaFileListRequest":"both","DJIWindowsWrapper.BottomAuxiliaryLightModeMsg":"both","DJIWindowsWrapper.FlysafeLicenseBaseInfo":"both","DJIWindowsWrapper.SpeakerAudioFileList":"both"}}},"Namespaces":{"DJIWindowsWrapper.__ISpeakerPlayModeTypeMsgPublicNonVirtuals":"DJIWindowsWrapper","DJIWindowsWrapper.OnCameraThermalPaletteRangeMsgResultDelegate":"DJIWindowsWrapper","DJIWindowsWrapper.__IBoolMsgPublicNonVirtuals":"DJIWindowsWrapper","DJIWindowsWrapper.OnAttitudeListenResultDelegate":"DJIWindowsWrapper","DJIWindowsWrapper.OnThermalAreaTemperatureAggregationsMsgResultDelegate":"DJIWindowsWrapper","DJIWindowsWrapper.__IGimbalAttitudeRangePublicNonVirtuals":"DJIWindowsWrapper","DJIWindowsWrapper.__IDJIWindowsLocationHandlePublicNonVirtuals":"DJIWindowsWrapper","DJIWindowsWrapper.OnFCFlightModeMsgListenResultDelegate":"DJIWindowsWrapper","DJIWindowsWrapper.OnWaypointMissionUploadStateDelegate":"DJIWindowsWrapper","DJIWindowsWrapper.__IFlysafeHeightLicenseInfoPublicNonVirtuals":"DJIWindowsWrapper","DJIWindowsWrapper.OnVissionDetectionStateResultDelegate":"DJIWindowsWrapper","DJIWindowsWrapper.__ICameraSDCardStateMsgPublicNonVirtuals":"DJIWindowsWrapper","DJIWindowsWrapper.DecodingAssistInfo":"DJIWindowsWrapper","DJIWindowsWrapper.__IBottomAuxiliaryLightModeMsgPublicNonVirtuals":"DJIWindowsWrapper","DJIWindowsWrapper.IMUMultipleOrientationCalibrationHint":"DJIWindowsWrapper","DJIWindowsWrapper.__IMediaStarTagRequestPublicNonVirtuals":"DJIWindowsWrapper","DJIWindowsWrapper.IntMinMax":"DJIWindowsWrapper","DJIWindowsWrapper.VideoResolutionFrameRate":"DJIWindowsWrapper","DJIWindowsWrapper.OnCameraThermalFFCModeMsgListenResultDelegate":"DJIWindowsWrapper","DJIWindowsWrapper.__ILocationCoordinate2DPublicNonVirtuals":"DJIWindowsWrapper","DJIWindowsWrapper.__IVideoStorageFormatMsgPublicNonVirtuals":"DJIWindowsWrapper","DJIWindowsWrapper.__ICameraPanoTypeMsgPublicNonVirtuals":"DJIWindowsWrapper","DJIWindowsWrapper.OnCameraAntiFlickerMsgResultDelegate":"DJIWindowsWrapper","DJIWindowsWrapper.FCMotorStartFailureErrorMsg":"DJIWindowsWrapper","DJIWindowsWrapper.OnFCRemoteControllerSwitchModeMsgResultDelegate":"DJIWindowsWrapper","DJIWindowsWrapper.__IGimbalResetCommandMsgPublicNonVirtuals":"DJIWindowsWrapper","DJIWindowsWrapper.__ICameraOrientationMsgPublicNonVirtuals":"DJIWindowsWrapper","DJIWindowsWrapper.OnCameraOpticalZoomSpecResultDelegate":"DJIWindowsWrapper","DJIWindowsWrapper.OnCameraTypeMsgResultDelegate":"DJIWindowsWrapper","DJIWindowsWrapper.NetworkHandleProgressResultDelegate":"DJIWindowsWrapper","DJIWindowsWrapper.OnFCWindWarningMsgResultDelegate":"DJIWindowsWrapper","DJIWindowsWrapper.OnGimbalAttitudeRangeListenResultDelegate":"DJIWindowsWrapper","DJIWindowsWrapper.LocationHandleStatusDelegate":"DJIWindowsWrapper","DJIWindowsWrapper.OnSpeakerAudioFilesIndexesResultDelegate":"DJIWindowsWrapper","DJIWindowsWrapper.OnBatteryHeatingStateMsgListenResultDelegate":"DJIWindowsWrapper","DJIWindowsWrapper.OnCameraShutterSpeedMsgListenResultDelegate":"DJIWindowsWrapper","DJIWindowsWrapper.DoubleMsg":"DJIWindowsWrapper","DJIWindowsWrapper.OnProductTypeMsgListenResultDelegate":"DJIWindowsWrapper","DJIWindowsWrapper.__ICameraThermalPaletteMsgPublicNonVirtuals":"DJIWindowsWrapper","DJIWindowsWrapper.__ICameraActualFocusAreaPublicNonVirtuals":"DJIWindowsWrapper","DJIWindowsWrapper.OnCameraMeteringModeMsgResultDelegate":"DJIWindowsWrapper","DJIWindowsWrapper.__IMediaFileListPublicNonVirtuals":"DJIWindowsWrapper","DJIWindowsWrapper.OnIntMinMaxResultDelegate":"DJIWindowsWrapper","DJIWindowsWrapper.SpeakerAudioFileUploadingInfo":"DJIWindowsWrapper","DJIWindowsWrapper.__IStringMsgPublicNonVirtuals":"DJIWindowsWrapper","DJIWindowsWrapper.OnCameraWatermarkSettingsResultDelegate":"DJIWindowsWrapper","DJIWindowsWrapper.OnCameraAntiFlickerMsgListenResultDelegate":"DJIWindowsWrapper","DJIWindowsWrapper.NetworkHandleGetterDelegate":"DJIWindowsWrapper","DJIWindowsWrapper.CameraColorRangeMsg":"DJIWindowsWrapper","DJIWindowsWrapper.__IIntPoint2DPublicNonVirtuals":"DJIWindowsWrapper","DJIWindowsWrapper.OnIntPoint2DResultDelegate":"DJIWindowsWrapper","DJIWindowsWrapper.__ISpeakerAudioSendingStateMsgPublicNonVirtuals":"DJIWindowsWrapper","DJIWindowsWrapper.OnVideoDataPushDelegate":"DJIWindowsWrapper","DJIWindowsWrapper.GimbalAngleRotation":"DJIWindowsWrapper","DJIWindowsWrapper.__ICameraColorRangeMsgPublicNonVirtuals":"DJIWindowsWrapper","DJIWindowsWrapper.__IDecodingAssistInfoPublicNonVirtuals":"DJIWindowsWrapper","DJIWindowsWrapper.OnCameraOrientationMsgResultDelegate":"DJIWindowsWrapper","DJIWindowsWrapper.OnPhotoIntervalShootSettingsListenResultDelegate":"DJIWindowsWrapper","DJIWindowsWrapper.__ICameraThermalFFCModeMsgPublicNonVirtuals":"DJIWindowsWrapper","DJIWindowsWrapper.OnCameraWhiteBalanceResultDelegate":"DJIWindowsWrapper","DJIWindowsWrapper.OnFCGPSModeFailureReasonMsgResultDelegate":"DJIWindowsWrapper","DJIWindowsWrapper.__ICameraThermalPaletteRangeMsgPublicNonVirtuals":"DJIWindowsWrapper","DJIWindowsWrapper.OnCameraWhiteBalanceListenResultDelegate":"DJIWindowsWrapper","DJIWindowsWrapper.OnSpeakerAudioFileListResultDelegate":"DJIWindowsWrapper","DJIWindowsWrapper.OnAccessLockerFormattingProgressStateMsgListenResultDelegate":"DJIWindowsWrapper","DJIWindowsWrapper.__IGimbalCalibrationStatePublicNonVirtuals":"DJIWindowsWrapper","DJIWindowsWrapper.__IPhotoIntervalShootSettingsPublicNonVirtuals":"DJIWindowsWrapper","DJIWindowsWrapper.__IGimbalSpeedRotationPublicNonVirtuals":"DJIWindowsWrapper","DJIWindowsWrapper.__IWaypointMissionPublicNonVirtuals":"DJIWindowsWrapper","DJIWindowsWrapper.__IFCGPSSignalLevelMsgPublicNonVirtuals":"DJIWindowsWrapper","DJIWindowsWrapper.OnCameraColorRangeMsgListenResultDelegate":"DJIWindowsWrapper","DJIWindowsWrapper.OnPhotoBurstCountMsgListenResultDelegate":"DJIWindowsWrapper","DJIWindowsWrapper.__IFlysafeCircleLicenseInfoPublicNonVirtuals":"DJIWindowsWrapper","DJIWindowsWrapper.__IMediaDeletionRequestPublicNonVirtuals":"DJIWindowsWrapper","DJIWindowsWrapper.__IMediaTaskRequestPublicNonVirtuals":"DJIWindowsWrapper","DJIWindowsWrapper.GimbalAttitudeRange":"DJIWindowsWrapper","DJIWindowsWrapper.OnProductTypeMsgResultDelegate":"DJIWindowsWrapper","DJIWindowsWrapper.OnCameraAutoTurnOffLEDModeMsgResultDelegate":"DJIWindowsWrapper","DJIWindowsWrapper.CameraDisplayModeMsg":"DJIWindowsWrapper","DJIWindowsWrapper.OnCameraTypeMsgListenResultDelegate":"DJIWindowsWrapper","DJIWindowsWrapper.SpeakerAudioDataSendingResultMsg":"DJIWindowsWrapper","DJIWindowsWrapper.CameraThermalPaletteRangeMsg":"DJIWindowsWrapper","DJIWindowsWrapper.__ISimulatorInitializationSettingsPublicNonVirtuals":"DJIWindowsWrapper","DJIWindowsWrapper.__ICameraThermalGainModeMsgPublicNonVirtuals":"DJIWindowsWrapper","DJIWindowsWrapper.OnLocationCoordinate2DResultDelegate":"DJIWindowsWrapper","DJIWindowsWrapper.DatalinkHandlerUnInitializeDelegate":"DJIWindowsWrapper","DJIWindowsWrapper.CameraExposureCompensationMsg":"DJIWindowsWrapper","DJIWindowsWrapper.CameraTemperatureUnitMsg":"DJIWindowsWrapper","DJIWindowsWrapper.PhotoBurstCountMsg":"DJIWindowsWrapper","DJIWindowsWrapper.OnBatteryHeatingStateMsgResultDelegate":"DJIWindowsWrapper","DJIWindowsWrapper.WaypointMissionExecutionState":"DJIWindowsWrapper","DJIWindowsWrapper.OnCameraPanoTypeMsgResultDelegate":"DJIWindowsWrapper","DJIWindowsWrapper.OnPlayingAudioFileInfoListenResultDelegate":"DJIWindowsWrapper","DJIWindowsWrapper.OnCameraISOMsgResultDelegate":"DJIWindowsWrapper","DJIWindowsWrapper.OnIntPoint2DListenResultDelegate":"DJIWindowsWrapper","DJIWindowsWrapper.OnFCRemoteControllerSwitchModeMsgListenResultDelegate":"DJIWindowsWrapper","DJIWindowsWrapper.__IVisionSystemWarningMsgPublicNonVirtuals":"DJIWindowsWrapper","DJIWindowsWrapper.OnSpeakerAudioSendingStateMsgResultDelegate":"DJIWindowsWrapper","DJIWindowsWrapper.OnCameraTemperatureUnitMsgResultDelegate":"DJIWindowsWrapper","DJIWindowsWrapper.BatteryHeatingStateMsg":"DJIWindowsWrapper","DJIWindowsWrapper.OnCameraThermalROIMsgResultDelegate":"DJIWindowsWrapper","DJIWindowsWrapper.OnVideoFileCompressionStandardMsgListenResultDelegate":"DJIWindowsWrapper","DJIWindowsWrapper.DJIWindowsWrappedInterfaces":"DJIWindowsWrapper","DJIWindowsWrapper.BoolMsg":"DJIWindowsWrapper","DJIWindowsWrapper.OnSpeakerPlayModeTypeMsgResultDelegate":"DJIWindowsWrapper","DJIWindowsWrapper.OnFCGPSSignalLevelMsgResultDelegate":"DJIWindowsWrapper","DJIWindowsWrapper.MediaTaskRequest":"DJIWindowsWrapper","DJIWindowsWrapper.__ISpeakerAudioFilesIndexesPublicNonVirtuals":"DJIWindowsWrapper","DJIWindowsWrapper.WaypointMission":"DJIWindowsWrapper","DJIWindowsWrapper.__IMediaFilePublicNonVirtuals":"DJIWindowsWrapper","DJIWindowsWrapper.AccessLockerFormattingProgressStateMsg":"DJIWindowsWrapper","DJIWindowsWrapper.USBHandlerUnInitializeDelegate":"DJIWindowsWrapper","DJIWindowsWrapper.CameraISOMsg":"DJIWindowsWrapper","DJIWindowsWrapper.OnFCAutoRTHReasonMsgResultDelegate":"DJIWindowsWrapper","DJIWindowsWrapper.__IVelocity3DPublicNonVirtuals":"DJIWindowsWrapper","DJIWindowsWrapper.OnCameraThermalPaletteRangeMsgListenResultDelegate":"DJIWindowsWrapper","DJIWindowsWrapper.OnRCFlightModeSwitchMsgListenResultDelegate":"DJIWindowsWrapper","DJIWindowsWrapper.MediaTaskResponse":"DJIWindowsWrapper","DJIWindowsWrapper.OnCameraOrientationMsgListenResultDelegate":"DJIWindowsWrapper","DJIWindowsWrapper.DatalinkHandlerOnRecvVideoDelegate":"DJIWindowsWrapper","DJIWindowsWrapper.IMUState":"DJIWindowsWrapper","DJIWindowsWrapper.OnIMUStatesListenResultDelegate":"DJIWindowsWrapper","DJIWindowsWrapper.VissionDetectionState":"DJIWindowsWrapper","DJIWindowsWrapper.OnAccountNetworkMgrPushedDelegate":"DJIWindowsWrapper","DJIWindowsWrapper.USBHandlerOnDeviceAddDelegate":"DJIWindowsWrapper","DJIWindowsWrapper.SDKActivationInfo":"DJIWindowsWrapper","DJIWindowsWrapper.IntPoint2D":"DJIWindowsWrapper","DJIWindowsWrapper.OnVideoStorageFormatMsgListenResultDelegate":"DJIWindowsWrapper","DJIWindowsWrapper.OnWaypointMissionDownloadStateDelegate":"DJIWindowsWrapper","DJIWindowsWrapper.WiFiFrequencyBandMsg":"DJIWindowsWrapper","DJIWindowsWrapper.GoHomeAssessmentValue":"DJIWindowsWrapper","DJIWindowsWrapper.__ICameraShootPhotoModeMsgPublicNonVirtuals":"DJIWindowsWrapper","DJIWindowsWrapper.ObstacleDetectionSector":"DJIWindowsWrapper","DJIWindowsWrapper.CameraExposureModeMsg":"DJIWindowsWrapper","DJIWindowsWrapper.__IPhotoBurstCountMsgPublicNonVirtuals":"DJIWindowsWrapper","DJIWindowsWrapper.__ICameraAntiFlickerMsgPublicNonVirtuals":"DJIWindowsWrapper","DJIWindowsWrapper.OnCameraActualFocusAreaResultDelegate":"DJIWindowsWrapper","DJIWindowsWrapper.CameraAntiFlickerMsg":"DJIWindowsWrapper","DJIWindowsWrapper.OnCameraShutterSpeedMsgResultDelegate":"DJIWindowsWrapper","DJIWindowsWrapper.CameraWhiteBalance":"DJIWindowsWrapper","DJIWindowsWrapper.__IThermalAreaTemperatureAggregationsMsgPublicNonVirtuals":"DJIWindowsWrapper","DJIWindowsWrapper.__IVissionDetectionStatePublicNonVirtuals":"DJIWindowsWrapper","DJIWindowsWrapper.__IIMUMultipleOrientationCalibrationHintPublicNonVirtuals":"DJIWindowsWrapper","DJIWindowsWrapper.OnPhotoStorageFormatMsgListenResultDelegate":"DJIWindowsWrapper","DJIWindowsWrapper.NetworkHandleResultDelegate":"DJIWindowsWrapper","DJIWindowsWrapper.IMUStates":"DJIWindowsWrapper","DJIWindowsWrapper.FlysafeLimitArea":"DJIWindowsWrapper","DJIWindowsWrapper.DoublePoint2D":"DJIWindowsWrapper","DJIWindowsWrapper.FlySafeSourroundingAreasDelegate":"DJIWindowsWrapper","DJIWindowsWrapper.CameraPanoTypeMsg":"DJIWindowsWrapper","DJIWindowsWrapper.MediaFileDownloadRequest":"DJIWindowsWrapper","DJIWindowsWrapper.CameraFocusModeMsg":"DJIWindowsWrapper","DJIWindowsWrapper.OnVelocity3DResultDelegate":"DJIWindowsWrapper","DJIWindowsWrapper.OnSpeakerAudioSendingStateMsgListenResultDelegate":"DJIWindowsWrapper","DJIWindowsWrapper.PlayingAudioFileInfo":"DJIWindowsWrapper","DJIWindowsWrapper.OnFCGoHomeStateMsgListenResultDelegate":"DJIWindowsWrapper","DJIWindowsWrapper.FlysafeHeightLicenseInfo":"DJIWindowsWrapper","DJIWindowsWrapper.OnCameraThermalROIMsgListenResultDelegate":"DJIWindowsWrapper","DJIWindowsWrapper.OnCameraColorMsgListenResultDelegate":"DJIWindowsWrapper","DJIWindowsWrapper.LandingProtectionStateMsg":"DJIWindowsWrapper","DJIWindowsWrapper.__IDJIWindowsUSBHandlerPublicNonVirtuals":"DJIWindowsWrapper","DJIWindowsWrapper.OnCameraShootPhotoModeMsgResultDelegate":"DJIWindowsWrapper","DJIWindowsWrapper.OnCameraFileIndexModeMsgListenResultDelegate":"DJIWindowsWrapper","DJIWindowsWrapper.ThermalAreaTemperatureAggregationsMsg":"DJIWindowsWrapper","DJIWindowsWrapper.__IFlysafePolygonLicenseInfoPublicNonVirtuals":"DJIWindowsWrapper","DJIWindowsWrapper.DoublePoint3D":"DJIWindowsWrapper","DJIWindowsWrapper.__IGoHomeAssessmentValuePublicNonVirtuals":"DJIWindowsWrapper","DJIWindowsWrapper.OnVissionDetectionStateListenResultDelegate":"DJIWindowsWrapper","DJIWindowsWrapper.OnFCBatteryThresholdBehaviorMsgListenResultDelegate":"DJIWindowsWrapper","DJIWindowsWrapper.Attitude":"DJIWindowsWrapper","DJIWindowsWrapper.__IBatteryHeatingStateMsgPublicNonVirtuals":"DJIWindowsWrapper","DJIWindowsWrapper.OnIMUStatesResultDelegate":"DJIWindowsWrapper","DJIWindowsWrapper.StringMsg":"DJIWindowsWrapper","DJIWindowsWrapper.EmptyMsg":"DJIWindowsWrapper","DJIWindowsWrapper.__IAttitudePublicNonVirtuals":"DJIWindowsWrapper","DJIWindowsWrapper.CameraThermalIsothermUnitMsg":"DJIWindowsWrapper","DJIWindowsWrapper.FlySafeGetAreaDelegate":"DJIWindowsWrapper","DJIWindowsWrapper.__IObstacleDetectionSectorPublicNonVirtuals":"DJIWindowsWrapper","DJIWindowsWrapper.__IFCGPSModeFailureReasonMsgPublicNonVirtuals":"DJIWindowsWrapper","DJIWindowsWrapper.ProductTypeMsg":"DJIWindowsWrapper","DJIWindowsWrapper.DatalinkHandlerInitializeDelegate":"DJIWindowsWrapper","DJIWindowsWrapper.__IFlysafeLicenseGroupMsgPublicNonVirtuals":"DJIWindowsWrapper","DJIWindowsWrapper.__IDJIWindowsWrapperComponentHandlerPublicNonVirtuals":"DJIWindowsWrapper","DJIWindowsWrapper.__IDoubleMsgPublicNonVirtuals":"DJIWindowsWrapper","DJIWindowsWrapper.OnCameraDisplayModeMsgResultDelegate":"DJIWindowsWrapper","DJIWindowsWrapper.__IMediaBatchFileRequestResultPublicNonVirtuals":"DJIWindowsWrapper","DJIWindowsWrapper.DJIWindowsWrapperComponentHandler":"DJIWindowsWrapper","DJIWindowsWrapper.__IAccessLockerUserAccountInfoMsgPublicNonVirtuals":"DJIWindowsWrapper","DJIWindowsWrapper.OnFCFlightModeMsgResultDelegate":"DJIWindowsWrapper","DJIWindowsWrapper.GeneratedMediaFileInfo":"DJIWindowsWrapper","DJIWindowsWrapper.CameraColorMsg":"DJIWindowsWrapper","DJIWindowsWrapper.OnGimbalCalibrationStateListenResultDelegate":"DJIWindowsWrapper","DJIWindowsWrapper.__ICameraFocusStateMsgPublicNonVirtuals":"DJIWindowsWrapper","DJIWindowsWrapper.LocationStatusDelegate":"DJIWindowsWrapper","DJIWindowsWrapper.__IPlayingAudioFileInfoPublicNonVirtuals":"DJIWindowsWrapper","DJIWindowsWrapper.__IDJIWindowsDatalinkHandlerPublicNonVirtuals":"DJIWindowsWrapper","DJIWindowsWrapper.OnGeneratedMediaFileInfoListenResultDelegate":"DJIWindowsWrapper","DJIWindowsWrapper.OnPhotoRatioMsgResultDelegate":"DJIWindowsWrapper","DJIWindowsWrapper.FCGoHomeStateMsg":"DJIWindowsWrapper","DJIWindowsWrapper.__IDJIWindowsWrapperComponentHandlerStatics":"DJIWindowsWrapper","DJIWindowsWrapper.AccessLockerUserAccountInfoMsg":"DJIWindowsWrapper","DJIWindowsWrapper.OnIntVector2DListenResultDelegate":"DJIWindowsWrapper","DJIWindowsWrapper.__ICameraISOMsgPublicNonVirtuals":"DJIWindowsWrapper","DJIWindowsWrapper.__IWaypointMissionUploadStatePublicNonVirtuals":"DJIWindowsWrapper","DJIWindowsWrapper.FlySafeOperationDelegate":"DJIWindowsWrapper","DJIWindowsWrapper.__ICameraWatermarkSettingsPublicNonVirtuals":"DJIWindowsWrapper","DJIWindowsWrapper.DoubleMinMax":"DJIWindowsWrapper","DJIWindowsWrapper.DatalinkHandlerOnRecvRawVideoDelegate":"DJIWindowsWrapper","DJIWindowsWrapper.FlysafeLicenseGroupMsg":"DJIWindowsWrapper","DJIWindowsWrapper.__IAccessLockerStateMsgPublicNonVirtuals":"DJIWindowsWrapper","DJIWindowsWrapper.OnVideoStorageFormatMsgResultDelegate":"DJIWindowsWrapper","DJIWindowsWrapper.SpeakerAudioSendingStateMsg":"DJIWindowsWrapper","DJIWindowsWrapper.__ICameraDisplayModeMsgPublicNonVirtuals":"DJIWindowsWrapper","DJIWindowsWrapper.__IFCFlightModeMsgPublicNonVirtuals":"DJIWindowsWrapper","DJIWindowsWrapper.__ICameraTemperatureUnitMsgPublicNonVirtuals":"DJIWindowsWrapper","DJIWindowsWrapper.USBHandlerOnRecvDataDelegate":"DJIWindowsWrapper","DJIWindowsWrapper.VideoFileCompressionStandardMsg":"DJIWindowsWrapper","DJIWindowsWrapper.OnGimbalCalibrationStateResultDelegate":"DJIWindowsWrapper","DJIWindowsWrapper.__ICameraMeteringModeMsgPublicNonVirtuals":"DJIWindowsWrapper","DJIWindowsWrapper.DateTime":"DJIWindowsWrapper","DJIWindowsWrapper.OnFCCompassCalibrationStateMsgResultDelegate":"DJIWindowsWrapper","DJIWindowsWrapper.DatalinkHandlerOnDeviceAddDelegate":"DJIWindowsWrapper","DJIWindowsWrapper.OnCameraThermalMeasurementModeMsgResultDelegate":"DJIWindowsWrapper","DJIWindowsWrapper.__IFCMotorStartFailureErrorMsgPublicNonVirtuals":"DJIWindowsWrapper","DJIWindowsWrapper.__ICameraFileIndexModeMsgPublicNonVirtuals":"DJIWindowsWrapper","DJIWindowsWrapper.__ICameraExposureModeMsgPublicNonVirtuals":"DJIWindowsWrapper","DJIWindowsWrapper.__ICameraStorageLocationMsgPublicNonVirtuals":"DJIWindowsWrapper","DJIWindowsWrapper.__IAirSenseAirplaneStatePublicNonVirtuals":"DJIWindowsWrapper","DJIWindowsWrapper.FCBatteryThresholdBehaviorMsg":"DJIWindowsWrapper","DJIWindowsWrapper.OnCameraExposureCompensationMsgResultDelegate":"DJIWindowsWrapper","DJIWindowsWrapper.__IVideoFileCompressionStandardMsgPublicNonVirtuals":"DJIWindowsWrapper","DJIWindowsWrapper.IntVector2D":"DJIWindowsWrapper","DJIWindowsWrapper.NetworkHandleDownloaderDelegate":"DJIWindowsWrapper","DJIWindowsWrapper.USBHandlerSendDataCallback":"DJIWindowsWrapper","DJIWindowsWrapper.OnCameraThermalFFCModeMsgResultDelegate":"DJIWindowsWrapper","DJIWindowsWrapper.OnFCFailsafeActionMsgResultDelegate":"DJIWindowsWrapper","DJIWindowsWrapper.FCCompassCalibrationStateMsg":"DJIWindowsWrapper","DJIWindowsWrapper.OnFCMotorStartFailureErrorMsgResultDelegate":"DJIWindowsWrapper","DJIWindowsWrapper.OnCameraThermalIsothermUnitMsgListenResultDelegate":"DJIWindowsWrapper","DJIWindowsWrapper.__IFCGoHomeStateMsgPublicNonVirtuals":"DJIWindowsWrapper","DJIWindowsWrapper.__IAccessLockerModifyAccountMsgPublicNonVirtuals":"DJIWindowsWrapper","DJIWindowsWrapper.NetworkHandlePosterDelegate":"DJIWindowsWrapper","DJIWindowsWrapper.__IFCBatteryThresholdBehaviorMsgPublicNonVirtuals":"DJIWindowsWrapper","DJIWindowsWrapper.__IMediaFileListLocationMsgPublicNonVirtuals":"DJIWindowsWrapper","DJIWindowsWrapper.__ICameraColorMsgPublicNonVirtuals":"DJIWindowsWrapper","DJIWindowsWrapper.OnCameraThermalIsothermUnitMsgResultDelegate":"DJIWindowsWrapper","DJIWindowsWrapper.__IGeneratedMediaFileInfoPublicNonVirtuals":"DJIWindowsWrapper","DJIWindowsWrapper.MediaBatchFileRequestResult":"DJIWindowsWrapper","DJIWindowsWrapper.OnPhotoStorageFormatMsgResultDelegate":"DJIWindowsWrapper","DJIWindowsWrapper.FlysafeAreaLicenseInfo":"DJIWindowsWrapper","DJIWindowsWrapper.OnPhotoIntervalShootSettingsResultDelegate":"DJIWindowsWrapper","DJIWindowsWrapper.OnCameraThermalGainModeMsgResultDelegate":"DJIWindowsWrapper","DJIWindowsWrapper.OnFCWindWarningMsgListenResultDelegate":"DJIWindowsWrapper","DJIWindowsWrapper.__IFlysafeLimitAreaPublicNonVirtuals":"DJIWindowsWrapper","DJIWindowsWrapper.__ICameraThermalMeasurementModeMsgPublicNonVirtuals":"DJIWindowsWrapper","DJIWindowsWrapper.LocationHandleResultDelegate":"DJIWindowsWrapper","DJIWindowsWrapper.__ICameraAutoTurnOffLEDModeMsgPublicNonVirtuals":"DJIWindowsWrapper","DJIWindowsWrapper.OnWiFiFrequencyBandMsgResultDelegate":"DJIWindowsWrapper","DJIWindowsWrapper.OnCameraWorkModeMsgResultDelegate":"DJIWindowsWrapper","DJIWindowsWrapper.CameraShootPhotoModeMsg":"DJIWindowsWrapper","DJIWindowsWrapper.OnSingalStringResDelegate":"DJIWindowsWrapper","DJIWindowsWrapper.OnVideoResolutionFrameRateListenResultDelegate":"DJIWindowsWrapper","DJIWindowsWrapper.OnMgrUpdateDelegate":"DJIWindowsWrapper","DJIWindowsWrapper.OnCameraFileIndexModeMsgResultDelegate":"DJIWindowsWrapper","DJIWindowsWrapper.DJIWindowsLocationHandle":"DJIWindowsWrapper","DJIWindowsWrapper.AppActivationState":"DJIWindowsWrapper","DJIWindowsWrapper.NetworkHandleStatusDelegate":"DJIWindowsWrapper","DJIWindowsWrapper.OnFCFailsafeActionMsgListenResultDelegate":"DJIWindowsWrapper","DJIWindowsWrapper.OnErrorResultDelegate":"DJIWindowsWrapper","DJIWindowsWrapper.__ISpeakerAudioFileUploadingInfoPublicNonVirtuals":"DJIWindowsWrapper","DJIWindowsWrapper.__IPhotoStorageFormatMsgPublicNonVirtuals":"DJIWindowsWrapper","DJIWindowsWrapper.OnSpeakerPlayModeTypeMsgListenResultDelegate":"DJIWindowsWrapper","DJIWindowsWrapper.SimulatorInitializationSettings":"DJIWindowsWrapper","DJIWindowsWrapper.USBHandlerSenddataDelegate":"DJIWindowsWrapper","DJIWindowsWrapper.AccessLockerModifyAccountMsg":"DJIWindowsWrapper","DJIWindowsWrapper.OnThermalAreaTemperatureAggregationsMsgListenResultDelegate":"DJIWindowsWrapper","DJIWindowsWrapper.VideoStorageFormatMsg":"DJIWindowsWrapper","DJIWindowsWrapper.__IFCCompassCalibrationStateMsgPublicNonVirtuals":"DJIWindowsWrapper","DJIWindowsWrapper.OnCameraExposureModeMsgResultDelegate":"DJIWindowsWrapper","DJIWindowsWrapper.__IDoublePoint2DPublicNonVirtuals":"DJIWindowsWrapper","DJIWindowsWrapper.CameraThermalROIMsg":"DJIWindowsWrapper","DJIWindowsWrapper.OnDoubleMsgResultDelegate":"DJIWindowsWrapper","DJIWindowsWrapper.__IWaypointMissionDownloadStatePublicNonVirtuals":"DJIWindowsWrapper","DJIWindowsWrapper.__IDateTimePublicNonVirtuals":"DJIWindowsWrapper","DJIWindowsWrapper.__ISpeakerAudioDeleteFilesInfoPublicNonVirtuals":"DJIWindowsWrapper","DJIWindowsWrapper.OnCameraFocusStateMsgResultDelegate":"DJIWindowsWrapper","DJIWindowsWrapper.FileExifInfo":"DJIWindowsWrapper","DJIWindowsWrapper.OnCameraThermalGainModeMsgListenResultDelegate":"DJIWindowsWrapper","DJIWindowsWrapper.DatalinkHandlerSenddataDelegate":"DJIWindowsWrapper","DJIWindowsWrapper.OnLEDsSettingsResultDelegate":"DJIWindowsWrapper","DJIWindowsWrapper.OnCameraDisplayModeMsgListenResultDelegate":"DJIWindowsWrapper","DJIWindowsWrapper.OnCameraTemperatureUnitMsgListenResultDelegate":"DJIWindowsWrapper","DJIWindowsWrapper.__IProductTypeMsgPublicNonVirtuals":"DJIWindowsWrapper","DJIWindowsWrapper.SpeakerPlayModeTypeMsg":"DJIWindowsWrapper","DJIWindowsWrapper.__IDJIWindowsWrappedInterfacesPublicNonVirtuals":"DJIWindowsWrapper","DJIWindowsWrapper.FCGPSSignalLevelMsg":"DJIWindowsWrapper","DJIWindowsWrapper.FlysafeCircleLicenseInfo":"DJIWindowsWrapper","DJIWindowsWrapper.__IFCAutoRTHReasonMsgPublicNonVirtuals":"DJIWindowsWrapper","DJIWindowsWrapper.OnCameraMeteringModeMsgListenResultDelegate":"DJIWindowsWrapper","DJIWindowsWrapper.CameraSDCardStateMsg":"DJIWindowsWrapper","DJIWindowsWrapper.USBHandlerOnDeviceRemoveDelegate":"DJIWindowsWrapper","DJIWindowsWrapper.OnAccessLockerStateMsgResultDelegate":"DJIWindowsWrapper","DJIWindowsWrapper.FCGPSModeFailureReasonMsg":"DJIWindowsWrapper","DJIWindowsWrapper.USBHandlerOnRecvRawVideoDelegate":"DJIWindowsWrapper","DJIWindowsWrapper.OnCameraFocusModeMsgResultDelegate":"DJIWindowsWrapper","DJIWindowsWrapper.__ICameraOpticalZoomSpecPublicNonVirtuals":"DJIWindowsWrapper","DJIWindowsWrapper.NetworkHandleDownloadResultDelegate":"DJIWindowsWrapper","DJIWindowsWrapper.OnCameraColorMsgResultDelegate":"DJIWindowsWrapper","DJIWindowsWrapper.OnCameraPanoTypeMsgListenResultDelegate":"DJIWindowsWrapper","DJIWindowsWrapper.__ISpeakerAudioFileListPublicNonVirtuals":"DJIWindowsWrapper","DJIWindowsWrapper.CameraOpticalZoomSpec":"DJIWindowsWrapper","DJIWindowsWrapper.CameraStorageLocationMsg":"DJIWindowsWrapper","DJIWindowsWrapper.LEDsSettings":"DJIWindowsWrapper","DJIWindowsWrapper.__IIMUStatesPublicNonVirtuals":"DJIWindowsWrapper","DJIWindowsWrapper.__IFileExifInfoPublicNonVirtuals":"DJIWindowsWrapper","DJIWindowsWrapper.CameraMeteringModeMsg":"DJIWindowsWrapper","DJIWindowsWrapper.CameraAutoTurnOffLEDModeMsg":"DJIWindowsWrapper","DJIWindowsWrapper.OnCameraOpticalZoomSpecListenResultDelegate":"DJIWindowsWrapper","DJIWindowsWrapper.OnFCGoHomeStateMsgResultDelegate":"DJIWindowsWrapper","DJIWindowsWrapper.AccessLockerStateMsg":"DJIWindowsWrapper","DJIWindowsWrapper.OnGoHomeAssessmentValueListenResultDelegate":"DJIWindowsWrapper","DJIWindowsWrapper.OnDoublePoint2DResultDelegate":"DJIWindowsWrapper","DJIWindowsWrapper.OnPhotoRatioMsgListenResultDelegate":"DJIWindowsWrapper","DJIWindowsWrapper.OnInitializeSuccessDelegate":"DJIWindowsWrapper","DJIWindowsWrapper.SpeakerAudioFilesIndexes":"DJIWindowsWrapper","DJIWindowsWrapper.LocationHandleGetterDelegate":"DJIWindowsWrapper","DJIWindowsWrapper.OnDoublePoint2DListenResultDelegate":"DJIWindowsWrapper","DJIWindowsWrapper.WaypointMissionStateTransition":"DJIWindowsWrapper","DJIWindowsWrapper.DJIWindowsDatalinkHandler":"DJIWindowsWrapper","DJIWindowsWrapper.FlySafeQueryLicenseIDDelegate":"DJIWindowsWrapper","DJIWindowsWrapper.FlysafeLicenseGroup":"DJIWindowsWrapper","DJIWindowsWrapper.__ICameraShutterSpeedMsgPublicNonVirtuals":"DJIWindowsWrapper","DJIWindowsWrapper.CameraShutterSpeedMsg":"DJIWindowsWrapper","DJIWindowsWrapper.CameraThermalFFCModeMsg":"DJIWindowsWrapper","DJIWindowsWrapper.OnDoubleMsgListenResultDelegate":"DJIWindowsWrapper","DJIWindowsWrapper.__ICameraContinuousOpticalZoomParamPublicNonVirtuals":"DJIWindowsWrapper","DJIWindowsWrapper.OnCameraSDCardStateMsgResultDelegate":"DJIWindowsWrapper","DJIWindowsWrapper.Waypoint":"DJIWindowsWrapper","DJIWindowsWrapper.__ICameraThermalIsothermUnitMsgPublicNonVirtuals":"DJIWindowsWrapper","DJIWindowsWrapper.GimbalResetCommandMsg":"DJIWindowsWrapper","DJIWindowsWrapper.__IDJIWindowsNetworkHandlePublicNonVirtuals":"DJIWindowsWrapper","DJIWindowsWrapper.DatalinkHandlerOnDeviceRemoveDelegate":"DJIWindowsWrapper","DJIWindowsWrapper.GimbalCalibrationState":"DJIWindowsWrapper","DJIWindowsWrapper.AirSenseAirplaneState":"DJIWindowsWrapper","DJIWindowsWrapper.__ILEDsSettingsPublicNonVirtuals":"DJIWindowsWrapper","DJIWindowsWrapper.OnGoHomeAssessmentValueResultDelegate":"DJIWindowsWrapper","DJIWindowsWrapper.CameraTypeMsg":"DJIWindowsWrapper","DJIWindowsWrapper.OnFCAutoRTHReasonMsgListenResultDelegate":"DJIWindowsWrapper","DJIWindowsWrapper.OnEmptyMsgResultDelegate":"DJIWindowsWrapper","DJIWindowsWrapper.__IVideoResolutionFrameRatePublicNonVirtuals":"DJIWindowsWrapper","DJIWindowsWrapper.OnFCGPSSignalLevelMsgListenResultDelegate":"DJIWindowsWrapper","DJIWindowsWrapper.FlysafePolygonLicenseInfo":"DJIWindowsWrapper","DJIWindowsWrapper.OnAccessLockerFormattingProgressStateMsgResultDelegate":"DJIWindowsWrapper","DJIWindowsWrapper.CameraWatermarkSettings":"DJIWindowsWrapper","DJIWindowsWrapper.__IFCFailsafeActionMsgPublicNonVirtuals":"DJIWindowsWrapper","DJIWindowsWrapper.OnCameraFocusStateMsgListenResultDelegate":"DJIWindowsWrapper","DJIWindowsWrapper.__ISpeakerAudioFileInfoPublicNonVirtuals":"DJIWindowsWrapper","DJIWindowsWrapper.__IWiFiFrequencyBandMsgPublicNonVirtuals":"DJIWindowsWrapper","DJIWindowsWrapper.__IGimbalAngleRotationPublicNonVirtuals":"DJIWindowsWrapper","DJIWindowsWrapper.MediaFileList":"DJIWindowsWrapper","DJIWindowsWrapper.OnPlayingAudioFileInfoResultDelegate":"DJIWindowsWrapper","DJIWindowsWrapper.OnIntMinMaxListenResultDelegate":"DJIWindowsWrapper","DJIWindowsWrapper.RCFlightModeSwitchMsg":"DJIWindowsWrapper","DJIWindowsWrapper.OnCameraShootPhotoModeMsgListenResultDelegate":"DJIWindowsWrapper","DJIWindowsWrapper.WaypointAction":"DJIWindowsWrapper","DJIWindowsWrapper.FCWindWarningMsg":"DJIWindowsWrapper","DJIWindowsWrapper.OnVideoFileCompressionStandardMsgResultDelegate":"DJIWindowsWrapper","DJIWindowsWrapper.CameraWorkModeMsg":"DJIWindowsWrapper","DJIWindowsWrapper.__ISpeakerAudioDataPackPublicNonVirtuals":"DJIWindowsWrapper","DJIWindowsWrapper.DJIWindowsUSBHandler":"DJIWindowsWrapper","DJIWindowsWrapper.FCFlightModeMsg":"DJIWindowsWrapper","DJIWindowsWrapper.OnCameraStorageLocationMsgResultDelegate":"DJIWindowsWrapper","DJIWindowsWrapper.PhotoRatioMsg":"DJIWindowsWrapper","DJIWindowsWrapper.__IAccessLockerFormattingProgressStateMsgPublicNonVirtuals":"DJIWindowsWrapper","DJIWindowsWrapper.OnCameraThermalPaletteMsgResultDelegate":"DJIWindowsWrapper","DJIWindowsWrapper.DatalinkHandlerOnRecvDataDelegate":"DJIWindowsWrapper","DJIWindowsWrapper.OnRCFlightModeSwitchMsgResultDelegate":"DJIWindowsWrapper","DJIWindowsWrapper.__ICameraWorkModeMsgPublicNonVirtuals":"DJIWindowsWrapper","DJIWindowsWrapper.LocationCoordinate2D":"DJIWindowsWrapper","DJIWindowsWrapper.Velocity3D":"DJIWindowsWrapper","DJIWindowsWrapper.CameraFileIndexModeMsg":"DJIWindowsWrapper","DJIWindowsWrapper.PhotoStorageFormatMsg":"DJIWindowsWrapper","DJIWindowsWrapper.OnCameraHistogramResultDelegate":"DJIWindowsWrapper","DJIWindowsWrapper.MediaStarTagRequest":"DJIWindowsWrapper","DJIWindowsWrapper.GimbalSpeedRotation":"DJIWindowsWrapper","DJIWindowsWrapper.OnLandingProtectionStateMsgListenResultDelegate":"DJIWindowsWrapper","DJIWindowsWrapper.SpeakerAudioDeleteFilesInfo":"DJIWindowsWrapper","DJIWindowsWrapper.IntMsg":"DJIWindowsWrapper","DJIWindowsWrapper.OnCameraExposureModeMsgListenResultDelegate":"DJIWindowsWrapper","DJIWindowsWrapper.CameraOrientationMsg":"DJIWindowsWrapper","DJIWindowsWrapper.__IIMUStatePublicNonVirtuals":"DJIWindowsWrapper","DJIWindowsWrapper.OnIntMsgListenResultDelegate":"DJIWindowsWrapper","DJIWindowsWrapper.__IFlysafeLicenseBaseInfoPublicNonVirtuals":"DJIWindowsWrapper","DJIWindowsWrapper.OnBindingStateStateDelegate":"DJIWindowsWrapper","DJIWindowsWrapper.MediaFile":"DJIWindowsWrapper","DJIWindowsWrapper.OnLocationCoordinate2DListenResultDelegate":"DJIWindowsWrapper","DJIWindowsWrapper.FCAutoRTHReasonMsg":"DJIWindowsWrapper","DJIWindowsWrapper.OnBoolMsgListenResultDelegate":"DJIWindowsWrapper","DJIWindowsWrapper.AirSenseSystemInformation":"DJIWindowsWrapper","DJIWindowsWrapper.__IIntVector2DPublicNonVirtuals":"DJIWindowsWrapper","DJIWindowsWrapper.__IDoublePoint3DPublicNonVirtuals":"DJIWindowsWrapper","DJIWindowsWrapper.FlysafeLimitAreaMsg":"DJIWindowsWrapper","DJIWindowsWrapper.__IAirSenseSystemInformationPublicNonVirtuals":"DJIWindowsWrapper","DJIWindowsWrapper.__IIntMinMaxPublicNonVirtuals":"DJIWindowsWrapper","DJIWindowsWrapper.OnSpeakerAudioFileListListenResultDelegate":"DJIWindowsWrapper","DJIWindowsWrapper.__IFlysafeAreaLicenseInfoPublicNonVirtuals":"DJIWindowsWrapper","DJIWindowsWrapper.OnMediaTaskResponseDelegate":"DJIWindowsWrapper","DJIWindowsWrapper.__ISDKActivationInfoPublicNonVirtuals":"DJIWindowsWrapper","DJIWindowsWrapper.UwpDatalinkType":"DJIWindowsWrapper","DJIWindowsWrapper.OnCameraAutoTurnOffLEDModeMsgListenResultDelegate":"DJIWindowsWrapper","DJIWindowsWrapper.__ISpeakerAudioDataSendingResultMsgPublicNonVirtuals":"DJIWindowsWrapper","DJIWindowsWrapper.OnCameraFocusModeMsgListenResultDelegate":"DJIWindowsWrapper","DJIWindowsWrapper.USBHandlerInitializeDelegate":"DJIWindowsWrapper","DJIWindowsWrapper.OnStringMsgResultDelegate":"DJIWindowsWrapper","DJIWindowsWrapper.OnCameraThermalPaletteMsgListenResultDelegate":"DJIWindowsWrapper","DJIWindowsWrapper.WaypointMissionUploadState":"DJIWindowsWrapper","DJIWindowsWrapper.OnWaypointMissionStateDelegate":"DJIWindowsWrapper","DJIWindowsWrapper.OnCameraHistogramListenResultDelegate":"DJIWindowsWrapper","DJIWindowsWrapper.CameraContinuousOpticalZoomParam":"DJIWindowsWrapper","DJIWindowsWrapper.MediaDeletionRequest":"DJIWindowsWrapper","DJIWindowsWrapper.FCFailsafeActionMsg":"DJIWindowsWrapper","DJIWindowsWrapper.OnCameraColorRangeMsgResultDelegate":"DJIWindowsWrapper","DJIWindowsWrapper.MediaFileListLocationMsg":"DJIWindowsWrapper","DJIWindowsWrapper.FlySafeLocalLicenseGroupsFetchDelegate":"DJIWindowsWrapper","DJIWindowsWrapper.OnIntMsgResultDelegate":"DJIWindowsWrapper","DJIWindowsWrapper.OnSpeakerAudioDataSendingResultMsgResultDelegate":"DJIWindowsWrapper","DJIWindowsWrapper.__IDJIWindowsWrappedInterfacesStatics":"DJIWindowsWrapper","DJIWindowsWrapper.DJIWindowsNetworkHandle":"DJIWindowsWrapper","DJIWindowsWrapper.__IWaypointMissionExecutionStatePublicNonVirtuals":"DJIWindowsWrapper","DJIWindowsWrapper.WaypointMissionDownloadState":"DJIWindowsWrapper","DJIWindowsWrapper.OnFCMotorStartFailureErrorMsgListenResultDelegate":"DJIWindowsWrapper","DJIWindowsWrapper.CameraFocusStateMsg":"DJIWindowsWrapper","DJIWindowsWrapper.__IFCRemoteControllerSwitchModeMsgPublicNonVirtuals":"DJIWindowsWrapper","DJIWindowsWrapper.SpeakerAudioDataPack":"DJIWindowsWrapper","DJIWindowsWrapper.OnProductIDDelegate":"DJIWindowsWrapper","DJIWindowsWrapper.SpeakerFileRenameInfo":"DJIWindowsWrapper","DJIWindowsWrapper.SpeakerAudioFileInfo":"DJIWindowsWrapper","DJIWindowsWrapper.__ICameraThermalROIMsgPublicNonVirtuals":"DJIWindowsWrapper","DJIWindowsWrapper.FlySafeLicenseGroupFetchDelegate":"DJIWindowsWrapper","DJIWindowsWrapper.__IFlysafeLimitAreaMsgPublicNonVirtuals":"DJIWindowsWrapper","DJIWindowsWrapper.__IEmptyMsgPublicNonVirtuals":"DJIWindowsWrapper","DJIWindowsWrapper.__IWaypointActionPublicNonVirtuals":"DJIWindowsWrapper","DJIWindowsWrapper.__IFlysafeLicenseGroupPublicNonVirtuals":"DJIWindowsWrapper","DJIWindowsWrapper.CameraThermalMeasurementModeMsg":"DJIWindowsWrapper","DJIWindowsWrapper.OnWaypointMissionExecutionStateDelegate":"DJIWindowsWrapper","DJIWindowsWrapper.USBHandlerOnRecvVideoDelegate":"DJIWindowsWrapper","DJIWindowsWrapper.CameraActualFocusArea":"DJIWindowsWrapper","DJIWindowsWrapper.OnVelocity3DListenResultDelegate":"DJIWindowsWrapper","DJIWindowsWrapper.__IMediaFileDownloadRequestPublicNonVirtuals":"DJIWindowsWrapper","DJIWindowsWrapper.OnCameraExposureCompensationMsgListenResultDelegate":"DJIWindowsWrapper","DJIWindowsWrapper.__IFCWindWarningMsgPublicNonVirtuals":"DJIWindowsWrapper","DJIWindowsWrapper.OnPhotoBurstCountMsgResultDelegate":"DJIWindowsWrapper","DJIWindowsWrapper.OnAttitudeResultDelegate":"DJIWindowsWrapper","DJIWindowsWrapper.VisionSystemWarningMsg":"DJIWindowsWrapper","DJIWindowsWrapper.OnBoolMsgResultDelegate":"DJIWindowsWrapper","DJIWindowsWrapper.OnVideoResolutionFrameRateResultDelegate":"DJIWindowsWrapper","DJIWindowsWrapper.OnLEDsSettingsListenResultDelegate":"DJIWindowsWrapper","DJIWindowsWrapper.OnFCCompassCalibrationStateMsgListenResultDelegate":"DJIWindowsWrapper","DJIWindowsWrapper.OnFCBatteryThresholdBehaviorMsgResultDelegate":"DJIWindowsWrapper","DJIWindowsWrapper.OnCameraSDCardStateMsgListenResultDelegate":"DJIWindowsWrapper","DJIWindowsWrapper.__IPhotoRatioMsgPublicNonVirtuals":"DJIWindowsWrapper","DJIWindowsWrapper.__IWaypointPublicNonVirtuals":"DJIWindowsWrapper","DJIWindowsWrapper.__IFlysafeCountryLicenseInfoPublicNonVirtuals":"DJIWindowsWrapper","DJIWindowsWrapper.__ICameraExposureCompensationMsgPublicNonVirtuals":"DJIWindowsWrapper","DJIWindowsWrapper.OnGimbalAttitudeRangeResultDelegate":"DJIWindowsWrapper","DJIWindowsWrapper.OnFCGPSModeFailureReasonMsgListenResultDelegate":"DJIWindowsWrapper","DJIWindowsWrapper.FCRemoteControllerSwitchModeMsg":"DJIWindowsWrapper","DJIWindowsWrapper.__ICameraHistogramPublicNonVirtuals":"DJIWindowsWrapper","DJIWindowsWrapper.OnStringMsgListenResultDelegate":"DJIWindowsWrapper","DJIWindowsWrapper.CameraThermalGainModeMsg":"DJIWindowsWrapper","DJIWindowsWrapper.OnBottomAuxiliaryLightModeMsgResultDelegate":"DJIWindowsWrapper","DJIWindowsWrapper.__ICameraFocusModeMsgPublicNonVirtuals":"DJIWindowsWrapper","DJIWindowsWrapper.OnAppActivationStateDelegate":"DJIWindowsWrapper","DJIWindowsWrapper.FlysafeCountryLicenseInfo":"DJIWindowsWrapper","DJIWindowsWrapper.__IIntMsgPublicNonVirtuals":"DJIWindowsWrapper","DJIWindowsWrapper.OnIntVector2DResultDelegate":"DJIWindowsWrapper","DJIWindowsWrapper.OnAirSenseSystemInformationListenResultDelegate":"DJIWindowsWrapper","DJIWindowsWrapper.OnCameraISOMsgListenResultDelegate":"DJIWindowsWrapper","DJIWindowsWrapper.CameraThermalPaletteMsg":"DJIWindowsWrapper","DJIWindowsWrapper.__ICameraWhiteBalancePublicNonVirtuals":"DJIWindowsWrapper","DJIWindowsWrapper.OnAirSenseSystemInformationResultDelegate":"DJIWindowsWrapper","DJIWindowsWrapper.__ISpeakerFileRenameInfoPublicNonVirtuals":"DJIWindowsWrapper","DJIWindowsWrapper.OnCameraWorkModeMsgListenResultDelegate":"DJIWindowsWrapper","DJIWindowsWrapper.OnAccessLockerStateMsgListenResultDelegate":"DJIWindowsWrapper","DJIWindowsWrapper.__ICameraTypeMsgPublicNonVirtuals":"DJIWindowsWrapper","DJIWindowsWrapper.__IWaypointMissionStateTransitionPublicNonVirtuals":"DJIWindowsWrapper","DJIWindowsWrapper.OnCameraThermalMeasurementModeMsgListenResultDelegate":"DJIWindowsWrapper","DJIWindowsWrapper.OnLandingProtectionStateMsgResultDelegate":"DJIWindowsWrapper","DJIWindowsWrapper.__IMediaFileListRequestPublicNonVirtuals":"DJIWindowsWrapper","DJIWindowsWrapper.CameraHistogram":"DJIWindowsWrapper","DJIWindowsWrapper.PhotoIntervalShootSettings":"DJIWindowsWrapper","DJIWindowsWrapper.__IDoubleMinMaxPublicNonVirtuals":"DJIWindowsWrapper","DJIWindowsWrapper.MediaFileListRequest":"DJIWindowsWrapper","DJIWindowsWrapper.__IMediaTaskResponsePublicNonVirtuals":"DJIWindowsWrapper","DJIWindowsWrapper.FlySafeLicenseGroupsFetchDelegate":"DJIWindowsWrapper","DJIWindowsWrapper.OnCameraActualFocusAreaListenResultDelegate":"DJIWindowsWrapper","DJIWindowsWrapper.BottomAuxiliaryLightModeMsg":"DJIWindowsWrapper","DJIWindowsWrapper.FlysafeLicenseBaseInfo":"DJIWindowsWrapper","DJIWindowsWrapper.__ILandingProtectionStateMsgPublicNonVirtuals":"DJIWindowsWrapper","DJIWindowsWrapper.__IRCFlightModeSwitchMsgPublicNonVirtuals":"DJIWindowsWrapper","DJIWindowsWrapper.DatalinkHandlerSendDataCallback":"DJIWindowsWrapper","DJIWindowsWrapper.SpeakerAudioFileList":"DJIWindowsWrapper","DJIWindowsWrapper.OnSDKActivationResultDelegate":"DJIWindowsWrapper"},"RootNamespace":"DJIWindowsWrapper","AssemblyVersion":"15.0.28307.779"}